Metadata-Version: 2.1
Name: tab-gan-metrics
Version: 1.1.4
Summary: A package to evaluate how close a synthetic data set is to real data.
Home-page: https://github.com/ChillBoss/tab_gan_metrics
Author: Tavva Prudhvith
Author-email: iamsinglemap@gmail.com
License: UNKNOWN
Platform: UNKNOWN
Classifier: Programming Language :: Python :: 3.7
Classifier: Operating System :: OS Independent
